qr2text.py
qr2text-1.1.2.dist-info/METADATA
qr2text-1.1.2.dist-info/WHEEL
qr2text-1.1.2.dist-info/entry_points.txt
qr2text-1.1.2.dist-info/top_level.txt
qr2text-1.1.2.dist-info/RECORD
